{
  "_instructions": "About section.",
  "sectionTitle": "About Me",
  "image": "assets/images/profile.jpg",
  "paragraphs": [
    "Data Engineer with 2+ years of enterprise experience building reliable data pipelines and analytics-ready datasets.",
    "Strong in Python and SQL, data validation, and stakeholder-facing data definitions; MS in Computer Science (University of North Texas)."
  ],
  "statistics": [
    {
      "icon": "fas fa-project-diagram",
      "value": "8+",
      "label": "Projects Completed",
      "color": "#FF6B6B"
    },
    {
      "icon": "fas fa-briefcase",
      "value": "2+",
      "label": "Years Experience",
      "color": "#4ECDC4"
    },
    {
      "icon": "fas fa-code",
      "value": "15+",
      "label": "Technologies",
      "color": "#FFE66D"
    },
    {
      "icon": "fas fa-award",
      "value": "0+",
      "label": "Certifications",
      "color": "#A8DADC"
    }
  ],
  "downloadCV": {
    "text": "Download Resume",
    "href": "assets/files/resume.pdf",
    "icon": "fas fa-download"
  }
}